README.txt
ez_setup.py
setup.py
whs.commons.abc.egg-info/PKG-INFO
whs.commons.abc.egg-info/SOURCES.txt
whs.commons.abc.egg-info/dependency_links.txt
whs.commons.abc.egg-info/namespace_packages.txt
whs.commons.abc.egg-info/requires.txt
whs.commons.abc.egg-info/top_level.txt
whs/commons/abc/__init__.py
whs/commons/abc/deserializable.py
whs/commons/abc/dict_protocol.py
whs/commons/abc/dto.py
whs/commons/abc/enhancers.py
whs/commons/abc/serializable.py
whs/commons/abc/session.py
whs/commons/abc/type_registry.py