Metadata-Version: 1.1
Name: whs.commons.abc
Version: 0.7.0
Summary: Abstract base classes for enterprise and business usage
Home-page: https://devzone.itadmin.pl
Author: Filip Malczak
Author-email: filip(dot)malczak(at)gmail(dot)com
License: BSD license (http://opensource.org/licenses/bsd-license.php); owner: Web Harvesting Solutions Ltd; year: 2013
Platform: Any
Classifier: Development Status :: 5 - Production/Stable
Classifier: Intended Audience :: Developers
Classifier: License :: OSI Approved :: BSD License
Classifier: Natural Language :: English
Classifier: Operating System :: OS Independent
Classifier: Programming Language :: Python :: 3
Classifier: Topic :: Utilities
